kneedeepio/plugins/__init__.py
kneedeepio/plugins/version.py
kneedeepio/plugins/manager/__init__.py
kneedeepio/plugins/manager/exceptions.py
kneedeepio/plugins/manager/manager.py
kneedeepio/plugins/manager/pluginfactory.py
kneedeepio/plugins/plugin/__init__.py
kneedeepio/plugins/plugin/exampleloggingplugin.py
kneedeepio/plugins/plugin/plugin.py
kneedeepio/plugins/services/__init__.py
kneedeepio/plugins/services/configurationservice.py
kneedeepio/plugins/services/loggingservice.py
kneedeepio/plugins/services/metricsreportingservice.py
kneedeepio/plugins/services/objectdatastoreservice.py
kneedeepio_plugins-0.0.7.dist-info/LICENSE
kneedeepio_plugins-0.0.7.dist-info/METADATA
kneedeepio_plugins-0.0.7.dist-info/WHEEL
kneedeepio_plugins-0.0.7.dist-info/top_level.txt
kneedeepio_plugins-0.0.7.dist-info/RECORD
